chunkle/__init__.py
chunkle-0.3.0.dist-info/LICENSE
chunkle-0.3.0.dist-info/METADATA
chunkle-0.3.0.dist-info/WHEEL
chunkle-0.3.0.dist-info/RECORD
