Metadata-Version: 2.3
Name: chunkle
Version: 0.3.0
Summary: Chunk long text with policies.
License: MIT
Author: allen2c
Author-email: f1470891079@gmail.com
Requires-Python: >=3.11,<4
Classifier: License :: OSI Approved :: MIT License
Classifier: Programming Language :: Python :: 3
Classifier: Programming Language :: Python :: 3.11
Classifier: Programming Language :: Python :: 3.12
Classifier: Programming Language :: Python :: 3.13
Requires-Dist: codepress (>=0.2.2,<0.3.0)
Requires-Dist: tiktoken (>=0.1.0,<1.0.0)
